{
  "x-generator": "NSwag v13.16.0.0 (NJsonSchema v10.7.1.0 (Newtonsoft.Json v13.0.0.0))",
  "openapi": "3.0.0",
  "info": {
    "title": "MauiCleanTodos API",
    "version": "1.0.0"
  },
  "paths": {
    "/api/TodoItems": {
      "post": {
        "tags": [
          "TodoItems"
        ],
        "operationId": "TodoItems_Create",
        "requestBody": {
          "x-name": "item",
          "content": {
            "application/json": {
              "schema": {
                "$ref": "#/components/schemas/NewTodoItemDto"
              }
            }
          },
          "required": true,
          "x-position": 1
        },
        "responses": {
          "200": {
            "description": "",
            "content": {
              "application/json": {
                "schema": {
                  "type": "integer",
                  "format": "int32"
                }
              }
            }
          }
        },
        "security": [
          {
            "JWT": []
          }
        ]
      }
    },
    "/api/TodoItems/{id}": {
      "put": {
        "tags": [
          "TodoItems"
        ],
        "operationId": "TodoItems_Update",
        "parameters": [
          {
            "name": "id",
            "in": "path",
            "required": true,
            "schema": {
              "type": "integer",
              "format": "int32"
            },
            "x-position": 1
          }
        ],
        "requestBody": {
          "x-name": "item",
          "content": {
            "application/json": {
              "schema": {
                "$ref": "#/components/schemas/TodoItemDto"
              }
            }
          },
          "required": true,
          "x-position": 2
        },
        "responses": {
          "204": {
            "description": ""
          }
        },
        "security": [
          {
            "JWT": []
          }
        ]
      },
      "delete": {
        "tags": [
          "TodoItems"
        ],
        "operationId": "TodoItems_Delete",
        "parameters": [
          {
            "name": "id",
            "in": "path",
            "required": true,
            "schema": {
              "type": "integer",
              "format": "int32"
            },
            "x-position": 1
          }
        ],
        "responses": {
          "204": {
            "description": ""
          }
        },
        "security": [
          {
            "JWT": []
          }
        ]
      }
    },
    "/api/TodoItems/UpdateItemDetails": {
      "put": {
        "tags": [
          "TodoItems"
        ],
        "operationId": "TodoItems_UpdateItemDetails",
        "parameters": [
          {
            "name": "id",
            "in": "query",
            "schema": {
              "type": "integer",
              "format": "int32"
            },
            "x-position": 1
          }
        ],
        "requestBody": {
          "x-name": "item",
          "content": {
            "application/json": {
              "schema": {
                "$ref": "#/components/schemas/TodoItemDto"
              }
            }
          },
          "required": true,
          "x-position": 2
        },
        "responses": {
          "204": {
            "description": ""
          }
        },
        "security": [
          {
            "JWT": []
          }
        ]
      }
    },
    "/api/TodoLists": {
      "get": {
        "tags": [
          "TodoLists"
        ],
        "operationId": "TodoLists_Get",
        "responses": {
          "200": {
            "description": "",
            "content": {
              "application/json": {
                "schema": {
                  "$ref": "#/components/schemas/TodosVm"
                }
              }
            }
          }
        },
        "security": [
          {
            "JWT": []
          }
        ]
      },
      "post": {
        "tags": [
          "TodoLists"
        ],
        "operationId": "TodoLists_Create",
        "requestBody": {
          "x-name": "newTodo",
          "content": {
            "application/json": {
              "schema": {
                "$ref": "#/components/schemas/NewTodoDto"
              }
            }
          },
          "required": true,
          "x-position": 1
        },
        "responses": {
          "200": {
            "description": "",
            "content": {
              "application/json": {
                "schema": {
                  "type": "integer",
                  "format": "int32"
                }
              }
            }
          }
        },
        "security": [
          {
            "JWT": []
          }
        ]
      }
    },
    "/api/TodoLists/{id}": {
      "get": {
        "tags": [
          "TodoLists"
        ],
        "operationId": "TodoLists_Get2",
        "parameters": [
          {
            "name": "id",
            "in": "path",
            "required": true,
            "schema": {
              "type": "integer",
              "format": "int32"
            },
            "x-position": 1
          }
        ],
        "responses": {
          "200": {
            "description": "",
            "content": {
              "application/octet-stream": {
                "schema": {
                  "type": "string",
                  "format": "binary"
                }
              }
            }
          }
        },
        "security": [
          {
            "JWT": []
          }
        ]
      },
      "put": {
        "tags": [
          "TodoLists"
        ],
        "operationId": "TodoLists_Update",
        "parameters": [
          {
            "name": "id",
            "in": "path",
            "required": true,
            "schema": {
              "type": "integer",
              "format": "int32"
            },
            "x-position": 1
          }
        ],
        "requestBody": {
          "x-name": "summary",
          "content": {
            "application/json": {
              "schema": {
                "$ref": "#/components/schemas/TodoListSummaryDto"
              }
            }
          },
          "required": true,
          "x-position": 2
        },
        "responses": {
          "204": {
            "description": ""
          }
        },
        "security": [
          {
            "JWT": []
          }
        ]
      },
      "delete": {
        "tags": [
          "TodoLists"
        ],
        "operationId": "TodoLists_Delete",
        "parameters": [
          {
            "name": "id",
            "in": "path",
            "required": true,
            "schema": {
              "type": "integer",
              "format": "int32"
            },
            "x-position": 1
          }
        ],
        "responses": {
          "204": {
            "description": ""
          }
        },
        "security": [
          {
            "JWT": []
          }
        ]
      }
    },
    "/api/WeatherForecast": {
      "get": {
        "tags": [
          "WeatherForecast"
        ],
        "operationId": "WeatherForecast_Get",
        "responses": {
          "200": {
            "description": "",
            "content": {
              "application/json": {
                "schema": {
                  "type": "array",
                  "items": {
                    "$ref": "#/components/schemas/WeatherForecastDto"
                  }
                }
              }
            }
          }
        }
      }
    }
  },
  "components": {
    "schemas": {
      "NewTodoItemDto": {
        "type": "object",
        "additionalProperties": false,
        "properties": {
          "listId": {
            "type": "integer",
            "format": "int32"
          },
          "title": {
            "type": "string",
            "nullable": true
          }
        }
      },
      "TodoItemDto": {
        "type": "object",
        "additionalProperties": false,
        "properties": {
          "id": {
            "type": "integer",
            "format": "int32"
          },
          "listId": {
            "type": "integer",
            "format": "int32"
          },
          "title": {
            "type": "string",
            "nullable": true
          },
          "done": {
            "type": "boolean"
          },
          "priority": {
            "type": "integer",
            "format": "int32"
          },
          "note": {
            "type": "string",
            "nullable": true
          }
        }
      },
      "TodosVm": {
        "type": "object",
        "additionalProperties": false,
        "properties": {
          "priorityLevels": {
            "type": "array",
            "items": {
              "$ref": "#/components/schemas/PriorityLevelDto"
            }
          },
          "lists": {
            "type": "array",
            "items": {
              "$ref": "#/components/schemas/TodoListDto"
            }
          }
        }
      },
      "PriorityLevelDto": {
        "type": "object",
        "additionalProperties": false,
        "properties": {
          "value": {
            "type": "integer",
            "format": "int32"
          },
          "name": {
            "type": "string",
            "nullable": true
          }
        }
      },
      "TodoListDto": {
        "type": "object",
        "additionalProperties": false,
        "properties": {
          "id": {
            "type": "integer",
            "format": "int32"
          },
          "title": {
            "type": "string",
            "nullable": true
          },
          "colour": {
            "type": "string",
            "nullable": true
          },
          "items": {
            "type": "array",
            "items": {
              "$ref": "#/components/schemas/TodoItemDto"
            }
          }
        }
      },
      "NewTodoDto": {
        "type": "object",
        "additionalProperties": false,
        "properties": {
          "title": {
            "type": "string"
          },
          "colour": {
            "$ref": "#/components/schemas/Colours"
          }
        }
      },
      "Colours": {
        "type": "integer",
        "description": "",
        "x-enumNames": [
          "Blue",
          "Purple",
          "Grey",
          "Green",
          "Red",
          "Orange",
          "Yellow",
          "White"
        ],
        "enum": [
          6711039,
          10053324,
          10066329,
          13434777,
          16734003,
          16761600,
          16777062,
          16777215
        ]
      },
      "TodoListSummaryDto": {
        "type": "object",
        "additionalProperties": false,
        "properties": {
          "id": {
            "type": "integer",
            "format": "int32"
          },
          "title": {
            "type": "string"
          }
        }
      },
      "WeatherForecastDto": {
        "type": "object",
        "additionalProperties": false,
        "properties": {
          "date": {
            "type": "string",
            "format": "date-time"
          },
          "temperatureC": {
            "type": "integer",
            "format": "int32"
          },
          "temperatureF": {
            "type": "integer",
            "format": "int32"
          },
          "summary": {
            "type": "string",
            "nullable": true
          }
        }
      }
    },
    "securitySchemes": {
      "JWT": {
        "type": "apiKey",
        "description": "Type into the textbox: Bearer {your JWT token}.",
        "name": "Authorization",
        "in": "header"
      }
    }
  },
  "security": [
    {
      "JWT": []
    }
  ]
}